candle/__init__.py
candle/candle.py
dataload/__init__.py
dataload/loadassets.py
dataload/splicer.py
dataload/utils.py
pricefunctions-0.0.10.dist-info/LICENSE.txt
pricefunctions-0.0.10.dist-info/METADATA
pricefunctions-0.0.10.dist-info/WHEEL
pricefunctions-0.0.10.dist-info/top_level.txt
pricefunctions-0.0.10.dist-info/RECORD
