Metadata-Version: 2.1
Name: pricefunctions
Version: 0.0.10
Summary: tool that converts OHLC price tables to candles
Author: RichCoastTrading
License: MIT
Classifier: License :: OSI Approved :: MIT License
Classifier: Programming Language :: Python :: 3.12
Classifier: Operating System :: OS Independent
License-File: LICENSE.txt
Requires-Dist: pandas >=2.2.2
